muffin_grpc/__init__.py
muffin_grpc/py.typed
muffin_grpc/utils.py
muffin_grpc-0.9.1.dist-info/METADATA
muffin_grpc-0.9.1.dist-info/WHEEL
muffin_grpc-0.9.1.dist-info/RECORD
