Metadata-Version: 2.3
Name: muffin-grpc
Version: 0.9.1
Summary: GRPC support for Muffin framework.
License: MIT
Keywords: grpc,muffin,asyncio,asgi,web
Author: Kirill Klenov
Author-email: horneds@gmail.com
Requires-Python: >=3.10,<4.0
Classifier: Development Status :: 5 - Production/Stable
Classifier: Framework :: AsyncIO
Classifier: Intended Audience :: Developers
Classifier: License :: OSI Approved :: MIT License
Classifier: Programming Language :: Python
Classifier: Programming Language :: Python :: 3
Classifier: Programming Language :: Python :: 3.10
Classifier: Programming Language :: Python :: 3.11
Classifier: Programming Language :: Python :: 3.12
Classifier: Programming Language :: Python :: 3.13
Requires-Dist: attrs
Requires-Dist: grpcio (>=1,<2)
Requires-Dist: grpcio-tools (>=1,<2)
Requires-Dist: muffin
Requires-Dist: proto-schema-parser
Project-URL: Homepage, https://github.com/klen/muffin-grpc
Project-URL: Repository, https://github.com/klen/muffin-grpc
